setup.py
python/gumbo/__init__.py
python/gumbo/gumboc.py
python/gumbo/gumboc_tags.py
python/gumbo/gumboc_test.py
python/gumbo/html5lib_adapter.py
python/gumbo/html5lib_adapter_test.py
python/gumbo/libgumbo.dylib
python/gumbo/soup_adapter.py
python/gumbo/soup_adapter_test.py
python/gumbo.egg-info/PKG-INFO
python/gumbo.egg-info/SOURCES.txt
python/gumbo.egg-info/dependency_links.txt
python/gumbo.egg-info/not-zip-safe
python/gumbo.egg-info/top_level.txt