Metadata-Version: 1.1
Name: gumbo
Version: 0.10.0
Summary: Python bindings for Gumbo HTML parser
Home-page: http://github.com/google/gumbo-parser
Author: Jonathan Tang
Author-email: jonathan.d.tang@gmail.com
License: Apache 2.0
Keywords: gumbo html html5 parser google html5lib beautifulsoup
Platform: UNKNOWN
Classifier: Development Status :: 4 - Beta
Classifier: Intended Audience :: Developers
Classifier: License :: OSI Approved :: Apache Software License
Classifier: Operating System :: Unix
Classifier: Operating System :: POSIX :: Linux
Classifier: Programming Language :: C
Classifier: Programming Language :: Python
Classifier: Programming Language :: Python :: 2
Classifier: Programming Language :: Python :: 2.7
Classifier: Programming Language :: Python :: 3
Classifier: Programming Language :: Python :: 3.4
Classifier: Topic :: Software Development :: Libraries :: Python Modules
Classifier: Topic :: Text Processing :: Markup :: HTML
